{
  "_class": "shapeGroup",
  "booleanOperation": -1,
  "clippingMaskMode": 0,
  "do_objectID": "7D7B29A6-CCF6-4CF5-A291-F801286967BF",
  "exportOptions": {
    "_class": "exportOptions",
    "exportFormats": [
    ],
    "includedLayerIds": [
    ],
    "layerOptions": 0,
    "shouldTrim": false
  },
  "frame": {
    "_class": "rect",
    "constrainProportions": false,
    "height": 18.41611360144135,
    "width": 21.08141037902321,
    "x": 0.4531036565122211,
    "y": 0.1205591340489018
  },
  "groupLayout": {
    "_class": "MSImmutableFreeformGroupLayout"
  },
  "hasClickThrough": false,
  "hasClippingMask": true,
  "isFixedToViewport": false,
  "isFlippedHorizontal": false,
  "isFlippedVertical": false,
  "isLocked": false,
  "isVisible": true,
  "layerListExpandedType": 1,
  "layers": [
    {
      "class": "shapePath",
      "id": "B3C722E5-DE57-4E92-8C23-3A2139A7673E"
    },
    {
      "class": "shapePath",
      "id": "2738C0B5-EE54-41B2-ABF0-0C46804F6E3F"
    },
    {
      "class": "shapePath",
      "id": "975B56EE-D79D-4E88-B8AC-0E199DF0E5E1"
    },
    {
      "class": "shapePath",
      "id": "8B3E1828-65D7-4746-91E0-69655D2E6B8A"
    },
    {
      "class": "shapePath",
      "id": "7DE2847F-016E-483E-83DC-0591F957001D"
    },
    {
      "class": "shapePath",
      "id": "E1DA67FC-A009-4DB4-87A8-6A664140D6CB"
    }
  ],
  "name": "Clip 1076",
  "nameIsFixed": false,
  "resizingConstraint": 63,
  "resizingType": 0,
  "rotation": 0,
  "shouldBreakMaskChain": false,
  "style": {
    "_class": "style",
    "blur": {
      "_class": "blur",
      "center": "{0.5, 0.5}",
      "isEnabled": false,
      "motionAngle": 0,
      "radius": 10,
      "saturation": 1,
      "type": 0
    },
    "borderOptions": {
      "_class": "borderOptions",
      "dashPattern": [
      ],
      "isEnabled": true,
      "lineCapStyle": 0,
      "lineJoinStyle": 0
    },
    "borders": [
    ],
    "colorControls": {
      "_class": "colorControls",
      "brightness": 0,
      "contrast": 1,
      "hue": 0,
      "isEnabled": false,
      "saturation": 1
    },
    "contextSettings": {
      "_class": "graphicsContextSettings",
      "blendMode": 0,
      "opacity": 1
    },
    "do_objectID": "7A09ED6A-0192-45E0-B9C9-8F2D92AFF4F2",
    "endMarkerType": 0,
    "fills": [
    ],
    "innerShadows": [
    ],
    "miterLimit": 10,
    "shadows": [
    ],
    "startMarkerType": 0,
    "windingRule": 1
  },
  "windingRule": 1
}