{
  "_class": "shapeGroup",
  "booleanOperation": -1,
  "clippingMaskMode": 0,
  "do_objectID": "EC340598-2397-4EC5-AFEB-8A7AF31D1E51",
  "exportOptions": {
    "_class": "exportOptions",
    "exportFormats": [
    ],
    "includedLayerIds": [
    ],
    "layerOptions": 0,
    "shouldTrim": false
  },
  "frame": {
    "_class": "rect",
    "constrainProportions": false,
    "height": 25.71530363251746,
    "width": 30.31186093458814,
    "x": 0.6514941257828786,
    "y": 0.1683425072649067
  },
  "groupLayout": {
    "_class": "MSImmutableFreeformGroupLayout"
  },
  "hasClickThrough": false,
  "hasClippingMask": true,
  "isFixedToViewport": false,
  "isFlippedHorizontal": false,
  "isFlippedVertical": false,
  "isLocked": false,
  "isVisible": true,
  "layerListExpandedType": 1,
  "layers": [
    {
      "class": "shapePath",
      "id": "70F6E84B-94E4-4DB9-907B-8AE94D3E4BFD"
    },
    {
      "class": "shapePath",
      "id": "F19D2ED9-557C-49B3-9862-2A7BF67C490B"
    },
    {
      "class": "shapePath",
      "id": "2C84631D-8997-4848-B5D1-3CB8AAACD46F"
    },
    {
      "class": "shapePath",
      "id": "8853C97F-A4CB-4E33-BCC3-F82E3CB4FBDB"
    },
    {
      "class": "shapePath",
      "id": "45D4BFA5-5BE2-43F5-971A-A2FF733DD28E"
    },
    {
      "class": "shapePath",
      "id": "ADCF7A16-D228-403E-A4C2-A6A05FDDEF59"
    }
  ],
  "name": "Clip 272",
  "nameIsFixed": false,
  "resizingConstraint": 63,
  "resizingType": 0,
  "rotation": 0,
  "shouldBreakMaskChain": false,
  "style": {
    "_class": "style",
    "blur": {
      "_class": "blur",
      "center": "{0.5, 0.5}",
      "isEnabled": false,
      "motionAngle": 0,
      "radius": 10,
      "saturation": 1,
      "type": 0
    },
    "borderOptions": {
      "_class": "borderOptions",
      "dashPattern": [
      ],
      "isEnabled": true,
      "lineCapStyle": 0,
      "lineJoinStyle": 0
    },
    "borders": [
    ],
    "colorControls": {
      "_class": "colorControls",
      "brightness": 0,
      "contrast": 1,
      "hue": 0,
      "isEnabled": false,
      "saturation": 1
    },
    "contextSettings": {
      "_class": "graphicsContextSettings",
      "blendMode": 0,
      "opacity": 1
    },
    "do_objectID": "A0154F13-0447-4DAE-8C91-A36614C15493",
    "endMarkerType": 0,
    "fills": [
    ],
    "innerShadows": [
    ],
    "miterLimit": 10,
    "shadows": [
    ],
    "startMarkerType": 0,
    "windingRule": 1
  },
  "windingRule": 1
}