{
  "_class": "shapeGroup",
  "booleanOperation": -1,
  "clippingMaskMode": 0,
  "do_objectID": "8F94998F-EE98-4B2D-A23F-DC4E10FC0924",
  "exportOptions": {
    "_class": "exportOptions",
    "exportFormats": [
    ],
    "includedLayerIds": [
    ],
    "layerOptions": 0,
    "shouldTrim": false
  },
  "frame": {
    "_class": "rect",
    "constrainProportions": false,
    "height": 18.41611360144135,
    "width": 21.08141037902321,
    "x": 0.4531036565122211,
    "y": 0.1205591340489018
  },
  "groupLayout": {
    "_class": "MSImmutableFreeformGroupLayout"
  },
  "hasClickThrough": false,
  "hasClippingMask": true,
  "isFixedToViewport": false,
  "isFlippedHorizontal": false,
  "isFlippedVertical": false,
  "isLocked": false,
  "isVisible": true,
  "layerListExpandedType": 1,
  "layers": [
    {
      "class": "shapePath",
      "id": "FB07F487-B1ED-4DB6-A441-794F8BA0E3B0"
    },
    {
      "class": "shapePath",
      "id": "24BF3D48-FC11-49DA-B740-21AE448CBA62"
    },
    {
      "class": "shapePath",
      "id": "B245524D-66F1-4592-80D3-6A9C7D5D77C8"
    },
    {
      "class": "shapePath",
      "id": "68D485F1-4F09-45ED-9659-94ADAA6F5795"
    },
    {
      "class": "shapePath",
      "id": "73F8D617-ED83-48B0-95EF-B56E5A17E00B"
    },
    {
      "class": "shapePath",
      "id": "5673695D-C0E6-4592-BA10-025DEEDEE494"
    }
  ],
  "name": "Clip 917",
  "nameIsFixed": false,
  "resizingConstraint": 63,
  "resizingType": 0,
  "rotation": 0,
  "shouldBreakMaskChain": false,
  "style": {
    "_class": "style",
    "blur": {
      "_class": "blur",
      "center": "{0.5, 0.5}",
      "isEnabled": false,
      "motionAngle": 0,
      "radius": 10,
      "saturation": 1,
      "type": 0
    },
    "borderOptions": {
      "_class": "borderOptions",
      "dashPattern": [
      ],
      "isEnabled": true,
      "lineCapStyle": 0,
      "lineJoinStyle": 0
    },
    "borders": [
    ],
    "colorControls": {
      "_class": "colorControls",
      "brightness": 0,
      "contrast": 1,
      "hue": 0,
      "isEnabled": false,
      "saturation": 1
    },
    "contextSettings": {
      "_class": "graphicsContextSettings",
      "blendMode": 0,
      "opacity": 1
    },
    "do_objectID": "F1D96BBA-A1A6-4559-B05C-FDD44ACCEA46",
    "endMarkerType": 0,
    "fills": [
    ],
    "innerShadows": [
    ],
    "miterLimit": 10,
    "shadows": [
    ],
    "startMarkerType": 0,
    "windingRule": 1
  },
  "windingRule": 1
}