{
  "_class": "shapeGroup",
  "booleanOperation": -1,
  "clippingMaskMode": 0,
  "do_objectID": "A0B94986-CDCC-46E9-A1FE-4993C8ADE76D",
  "exportOptions": {
    "_class": "exportOptions",
    "exportFormats": [
    ],
    "includedLayerIds": [
    ],
    "layerOptions": 0,
    "shouldTrim": false
  },
  "frame": {
    "_class": "rect",
    "constrainProportions": false,
    "height": 18.41611360144135,
    "width": 21.08141037902321,
    "x": 0.4531036565122211,
    "y": 0.1205591340489018
  },
  "groupLayout": {
    "_class": "MSImmutableFreeformGroupLayout"
  },
  "hasClickThrough": false,
  "hasClippingMask": true,
  "isFixedToViewport": false,
  "isFlippedHorizontal": false,
  "isFlippedVertical": false,
  "isLocked": false,
  "isVisible": true,
  "layerListExpandedType": 1,
  "layers": [
    {
      "class": "shapePath",
      "id": "797F52BF-1C29-4651-8111-2D9510090457"
    },
    {
      "class": "shapePath",
      "id": "30E08459-17DE-49F0-BAE1-F6E4BC07265D"
    },
    {
      "class": "shapePath",
      "id": "11E84434-FE46-4DDC-B5C8-B9DF31FCB9DA"
    },
    {
      "class": "shapePath",
      "id": "F0B35EF2-320F-470C-968A-047DB9866C55"
    },
    {
      "class": "shapePath",
      "id": "57B20455-5CB3-499D-A2A2-F28528EAECA9"
    },
    {
      "class": "shapePath",
      "id": "4935D213-7B6A-447E-8F9B-7286625504F5"
    }
  ],
  "name": "Clip 608",
  "nameIsFixed": false,
  "resizingConstraint": 63,
  "resizingType": 0,
  "rotation": 0,
  "shouldBreakMaskChain": false,
  "style": {
    "_class": "style",
    "blur": {
      "_class": "blur",
      "center": "{0.5, 0.5}",
      "isEnabled": false,
      "motionAngle": 0,
      "radius": 10,
      "saturation": 1,
      "type": 0
    },
    "borderOptions": {
      "_class": "borderOptions",
      "dashPattern": [
      ],
      "isEnabled": true,
      "lineCapStyle": 0,
      "lineJoinStyle": 0
    },
    "borders": [
    ],
    "colorControls": {
      "_class": "colorControls",
      "brightness": 0,
      "contrast": 1,
      "hue": 0,
      "isEnabled": false,
      "saturation": 1
    },
    "contextSettings": {
      "_class": "graphicsContextSettings",
      "blendMode": 0,
      "opacity": 1
    },
    "do_objectID": "C81F8F40-41FE-4078-82DF-BA413444F334",
    "endMarkerType": 0,
    "fills": [
    ],
    "innerShadows": [
    ],
    "miterLimit": 10,
    "shadows": [
    ],
    "startMarkerType": 0,
    "windingRule": 1
  },
  "windingRule": 1
}