{
  "_class": "shapeGroup",
  "booleanOperation": -1,
  "clippingMaskMode": 0,
  "do_objectID": "B0F893F1-D41D-459C-B8ED-C09D4245F6B9",
  "exportOptions": {
    "_class": "exportOptions",
    "exportFormats": [
    ],
    "includedLayerIds": [
    ],
    "layerOptions": 0,
    "shouldTrim": false
  },
  "frame": {
    "_class": "rect",
    "constrainProportions": false,
    "height": 25.71530363251746,
    "width": 30.31186093458814,
    "x": 0.6514941257828786,
    "y": 0.1683425072649067
  },
  "groupLayout": {
    "_class": "MSImmutableFreeformGroupLayout"
  },
  "hasClickThrough": false,
  "hasClippingMask": true,
  "isFixedToViewport": false,
  "isFlippedHorizontal": false,
  "isFlippedVertical": false,
  "isLocked": false,
  "isVisible": true,
  "layerListExpandedType": 1,
  "layers": [
    {
      "class": "shapePath",
      "id": "C774EFE0-20A6-4DE6-B6C5-9270C30011FA"
    },
    {
      "class": "shapePath",
      "id": "2F4DFF4A-C7F8-4A32-8F81-1D8EE257CAC1"
    },
    {
      "class": "shapePath",
      "id": "75E663FA-9743-4D50-99DA-F098E1DFA2F9"
    },
    {
      "class": "shapePath",
      "id": "0480B7F7-6003-48B4-98F5-22D476FBBAEA"
    },
    {
      "class": "shapePath",
      "id": "E0ADA19F-AB62-4BE1-83BE-9080E2799C87"
    },
    {
      "class": "shapePath",
      "id": "46F1AFE1-95A9-4542-A0E9-541A2B3306A0"
    }
  ],
  "name": "Clip 1487",
  "nameIsFixed": false,
  "resizingConstraint": 63,
  "resizingType": 0,
  "rotation": 0,
  "shouldBreakMaskChain": false,
  "style": {
    "_class": "style",
    "blur": {
      "_class": "blur",
      "center": "{0.5, 0.5}",
      "isEnabled": false,
      "motionAngle": 0,
      "radius": 10,
      "saturation": 1,
      "type": 0
    },
    "borderOptions": {
      "_class": "borderOptions",
      "dashPattern": [
      ],
      "isEnabled": true,
      "lineCapStyle": 0,
      "lineJoinStyle": 0
    },
    "borders": [
    ],
    "colorControls": {
      "_class": "colorControls",
      "brightness": 0,
      "contrast": 1,
      "hue": 0,
      "isEnabled": false,
      "saturation": 1
    },
    "contextSettings": {
      "_class": "graphicsContextSettings",
      "blendMode": 0,
      "opacity": 1
    },
    "do_objectID": "58791CB1-5F6C-46A7-8E8B-A6C62F6EB2F9",
    "endMarkerType": 0,
    "fills": [
    ],
    "innerShadows": [
    ],
    "miterLimit": 10,
    "shadows": [
    ],
    "startMarkerType": 0,
    "windingRule": 1
  },
  "windingRule": 1
}