{
  "_class": "group",
  "booleanOperation": -1,
  "clippingMaskMode": 0,
  "do_objectID": "AB8B9C9E-E159-4AEC-B42C-59DF25D77107",
  "exportOptions": {
    "_class": "exportOptions",
    "exportFormats": [
    ],
    "includedLayerIds": [
    ],
    "layerOptions": 0,
    "shouldTrim": false
  },
  "frame": {
    "_class": "rect",
    "constrainProportions": false,
    "height": 661,
    "width": 320,
    "x": 0,
    "y": -661
  },
  "groupLayout": {
    "_class": "MSImmutableFreeformGroupLayout"
  },
  "hasClickThrough": false,
  "hasClippingMask": false,
  "isFixedToViewport": false,
  "isFlippedHorizontal": false,
  "isFlippedVertical": false,
  "isLocked": false,
  "isVisible": true,
  "layerListExpandedType": 0,
  "layers": [
    {
      "class": "group",
      "id": "FF10DDF0-573E-4E82-A5E5-53B8AE43B871"
    },
    {
      "class": "group",
      "id": "DDA64925-A488-404A-9662-B06EA05E2579"
    },
    {
      "class": "group",
      "id": "D92499BF-6F74-4117-ADAC-C7B1F3AA8179"
    },
    {
      "class": "group",
      "id": "D932D2B5-0401-4EF2-A131-FD3BAABA3BA5"
    },
    {
      "class": "group",
      "id": "AC5ECA42-EDC8-4390-AC12-EC7D4FE8938A"
    },
    {
      "class": "text",
      "id": "9DC87CD2-9B7A-48CE-AE5A-D24ECFDDD482"
    },
    {
      "class": "text",
      "id": "5BD1FB7F-3B7C-4EE3-B78A-6C7C833750D2"
    },
    {
      "class": "group",
      "id": "BB427EC8-A4C8-48E0-9F7E-C13BEBB7F3DE"
    },
    {
      "class": "group",
      "id": "3B64B5BC-BA22-4AB8-91BE-92CF30EA6839"
    },
    {
      "class": "shapePath",
      "id": "372D0336-4EBC-4029-B944-4319D1B5A4AE"
    },
    {
      "class": "shapePath",
      "id": "E10309E6-B928-498F-8C8A-721A8222FE81"
    },
    {
      "class": "group",
      "id": "E2BEF77B-2A85-4542-88EA-9AB8B1218681"
    },
    {
      "class": "group",
      "id": "610D0BED-C761-49B9-B3A6-BFB397E9467C"
    }
  ],
  "name": "Pricesection",
  "nameIsFixed": true,
  "resizingConstraint": 63,
  "resizingType": 0,
  "rotation": 0,
  "shouldBreakMaskChain": false,
  "style": {
    "_class": "style",
    "blur": {
      "_class": "blur",
      "center": "{0.5, 0.5}",
      "isEnabled": false,
      "motionAngle": 0,
      "radius": 10,
      "saturation": 1,
      "type": 0
    },
    "borderOptions": {
      "_class": "borderOptions",
      "dashPattern": [
      ],
      "isEnabled": true,
      "lineCapStyle": 0,
      "lineJoinStyle": 0
    },
    "borders": [
    ],
    "colorControls": {
      "_class": "colorControls",
      "brightness": 0,
      "contrast": 1,
      "hue": 0,
      "isEnabled": false,
      "saturation": 1
    },
    "contextSettings": {
      "_class": "graphicsContextSettings",
      "blendMode": 0,
      "opacity": 1
    },
    "do_objectID": "5642D4DF-BDF7-4ACF-9880-61527DA09DD2",
    "endMarkerType": 0,
    "fills": [
    ],
    "innerShadows": [
    ],
    "miterLimit": 10,
    "shadows": [
    ],
    "startMarkerType": 0,
    "windingRule": 1
  }
}