{
  "_class": "shapeGroup",
  "booleanOperation": -1,
  "clippingMaskMode": 0,
  "do_objectID": "0EB4AA09-E62A-47B0-800A-771FFF3884D5",
  "exportOptions": {
    "_class": "exportOptions",
    "exportFormats": [
    ],
    "includedLayerIds": [
    ],
    "layerOptions": 0,
    "shouldTrim": false
  },
  "frame": {
    "_class": "rect",
    "constrainProportions": false,
    "height": 18.41611360144135,
    "width": 21.08141037902321,
    "x": 0.4531036565122211,
    "y": 0.1205591340489018
  },
  "groupLayout": {
    "_class": "MSImmutableFreeformGroupLayout"
  },
  "hasClickThrough": false,
  "hasClippingMask": true,
  "isFixedToViewport": false,
  "isFlippedHorizontal": false,
  "isFlippedVertical": false,
  "isLocked": false,
  "isVisible": true,
  "layerListExpandedType": 1,
  "layers": [
    {
      "class": "shapePath",
      "id": "B69F8F59-6517-4045-A85C-5EC6CB7952F0"
    },
    {
      "class": "shapePath",
      "id": "2B2DA75F-D1B8-4FA0-B5B5-35C5F7376503"
    },
    {
      "class": "shapePath",
      "id": "32EF6B07-67F3-404A-9D8E-81B233F1D91E"
    },
    {
      "class": "shapePath",
      "id": "19AB3138-30A9-4E5C-AFEF-9A7E195A6EE9"
    },
    {
      "class": "shapePath",
      "id": "614B2780-463B-40BA-AD4D-5AD429EE6A41"
    },
    {
      "class": "shapePath",
      "id": "004C40C4-8EFA-43E9-B9AF-70C44CDFAB09"
    }
  ],
  "name": "Clip 1115",
  "nameIsFixed": false,
  "resizingConstraint": 63,
  "resizingType": 0,
  "rotation": 0,
  "shouldBreakMaskChain": false,
  "style": {
    "_class": "style",
    "blur": {
      "_class": "blur",
      "center": "{0.5, 0.5}",
      "isEnabled": false,
      "motionAngle": 0,
      "radius": 10,
      "saturation": 1,
      "type": 0
    },
    "borderOptions": {
      "_class": "borderOptions",
      "dashPattern": [
      ],
      "isEnabled": true,
      "lineCapStyle": 0,
      "lineJoinStyle": 0
    },
    "borders": [
    ],
    "colorControls": {
      "_class": "colorControls",
      "brightness": 0,
      "contrast": 1,
      "hue": 0,
      "isEnabled": false,
      "saturation": 1
    },
    "contextSettings": {
      "_class": "graphicsContextSettings",
      "blendMode": 0,
      "opacity": 1
    },
    "do_objectID": "D20D5683-4C61-4746-A49E-C391E92D102D",
    "endMarkerType": 0,
    "fills": [
    ],
    "innerShadows": [
    ],
    "miterLimit": 10,
    "shadows": [
    ],
    "startMarkerType": 0,
    "windingRule": 1
  },
  "windingRule": 1
}